ZetcodeSpringJiaochengChuyi/README.md
ZetcodeSpringJiaochengChuyi/__init__.py
ZetcodeSpringJiaochengChuyi/__main__.py
ZetcodeSpringJiaochengChuyi/file.epub
ZetcodeSpringJiaochengChuyi/index.html
ZetcodeSpringJiaochengChuyi/css/__init__.py
ZetcodeSpringJiaochengChuyi/css/annotations.css
ZetcodeSpringJiaochengChuyi/css/main.css
ZetcodeSpringJiaochengChuyi/css/normalize.css
ZetcodeSpringJiaochengChuyi/css/popup.css
ZetcodeSpringJiaochengChuyi/font/__init__.py
ZetcodeSpringJiaochengChuyi/font/fontello.eot
ZetcodeSpringJiaochengChuyi/font/fontello.svg
ZetcodeSpringJiaochengChuyi/font/fontello.ttf
ZetcodeSpringJiaochengChuyi/font/fontello.woff
ZetcodeSpringJiaochengChuyi/img/__init__.py
ZetcodeSpringJiaochengChuyi/img/annotator-glyph-sprite.png
ZetcodeSpringJiaochengChuyi/img/annotator-icon-sprite.png
ZetcodeSpringJiaochengChuyi/img/apple-touch-icon.png
ZetcodeSpringJiaochengChuyi/img/cancelfullscreen.png
ZetcodeSpringJiaochengChuyi/img/close.png
ZetcodeSpringJiaochengChuyi/img/fullscreen.png
ZetcodeSpringJiaochengChuyi/img/loader.gif
ZetcodeSpringJiaochengChuyi/img/menu-icon.png
ZetcodeSpringJiaochengChuyi/img/save.png
ZetcodeSpringJiaochengChuyi/img/saved.png
ZetcodeSpringJiaochengChuyi/img/settings-s.png
ZetcodeSpringJiaochengChuyi/img/settings.png
ZetcodeSpringJiaochengChuyi/img/star.png
ZetcodeSpringJiaochengChuyi/js/__init__.py
ZetcodeSpringJiaochengChuyi/js/epub.js
ZetcodeSpringJiaochengChuyi/js/epub.min.js
ZetcodeSpringJiaochengChuyi/js/epub.min.map
ZetcodeSpringJiaochengChuyi/js/hooks.min.js
ZetcodeSpringJiaochengChuyi/js/hooks.min.map
ZetcodeSpringJiaochengChuyi/js/reader.js
ZetcodeSpringJiaochengChuyi/js/reader.js.map
ZetcodeSpringJiaochengChuyi/js/reader.min.js
ZetcodeSpringJiaochengChuyi/js/reader.min.map
ZetcodeSpringJiaochengChuyi/js/hooks/__init__.py
ZetcodeSpringJiaochengChuyi/js/hooks/extensions/__init__.py
ZetcodeSpringJiaochengChuyi/js/hooks/extensions/highlight.js
ZetcodeSpringJiaochengChuyi/js/libs/__init__.py
zetcode_spring_jiaocheng_chuyi-2024.3.5.0.dist-info/METADATA
zetcode_spring_jiaocheng_chuyi-2024.3.5.0.dist-info/WHEEL
zetcode_spring_jiaocheng_chuyi-2024.3.5.0.dist-info/entry_points.txt
zetcode_spring_jiaocheng_chuyi-2024.3.5.0.dist-info/top_level.txt
zetcode_spring_jiaocheng_chuyi-2024.3.5.0.dist-info/RECORD
